colorsnip-0.1.3.data/purelib/colorsnip.py
colorsnip-0.1.3.dist-info/METADATA
colorsnip-0.1.3.dist-info/RECORD
colorsnip-0.1.3.dist-info/WHEEL
colorsnip-0.1.3.dist-info/entry_points.txt
colorsnip-0.1.3.dist-info/top_level.txt
colorsnip-0.1.3.dist-info/zip-safe
