Metadata-Version: 2.1
Name: colorsnip
Version: 0.1.3
Summary: "Colorize snippets and copy to rich text clipboard"
Home-page: https://github.com/ewjoachim/colorsnip
Author: Joachim Jablon
Author-email: ewjoachim@gmail.com
License: MIT
Keywords: code,color,copy,clipboard,highlight,powerpoint,keynote
Platform: UNKNOWN
Classifier: Development Status :: 4 - Beta
Classifier: Intended Audience :: Developers
Classifier: License :: OSI Approved :: MIT License
Classifier: Natural Language :: English
Classifier: Programming Language :: Python :: 3
Classifier: Programming Language :: Python :: 3.4
Classifier: Programming Language :: Python :: 3.5
Provides-Extra: lint
Provides-Extra: test
Provides-Extra: dev
Requires-Dist: pygments
Requires-Dist: richxerox; platform_system == "Darwin"
Requires-Dist: klembord; platform_system == "Linux" or platform_system == "Windows"
Provides-Extra: dev
Requires-Dist: twine; extra == 'dev'
Provides-Extra: lint
Provides-Extra: test
